mini/__init__.py
mini/minifunc.py
minifunc-2.2.dist-info/LICENSE.txt
minifunc-2.2.dist-info/METADATA
minifunc-2.2.dist-info/WHEEL
minifunc-2.2.dist-info/top_level.txt
minifunc-2.2.dist-info/RECORD
