Metadata-Version: 2.1
Name: minifunc
Version: 2.2
Summary: MiniFunc
Home-page: UNKNOWN
Author: UNKNOWN
Author-email: UNKNOWN
License: UNKNOWN
Platform: UNKNOWN
